tinkerbin/__init__.py
tinkerbin/_version.py
tinkerbin/attr_class.py
tinkerbin/class_attributes.py
tinkerbin/dictionaries.py
tinkerbin/function_evaluation.py
tinkerbin/io.py
tinkerbin/ipython.py
tinkerbin/logging.py
tinkerbin/numerics_tools.py
tinkerbin/parameter_store.py
tinkerbin/printing.py
tinkerbin/printing_utils.py
tinkerbin/timer_utils.py
tinkerbin/timers.py
tinkerbin/utils.py
tinkerbin/numpy_tools/__init__.py
tinkerbin/numpy_tools/array_collection.py
tinkerbin/numpy_tools/mesh_collection.py
tinkerbin/numpy_tools/plotting.py
tinkerbin-0.1.0.dist-info/licenses/LICENSE
tinkerbin-0.1.0.dist-info/METADATA
tinkerbin-0.1.0.dist-info/WHEEL
tinkerbin-0.1.0.dist-info/top_level.txt
tinkerbin-0.1.0.dist-info/RECORD
