Metadata-Version: 2.4
Name: tinkerbin
Version: 0.1.0
Summary: A collection of utility tools for scientific computing and data analysis
Author: Jan Gulla, Odd Cappelen
License: LICENSE
Requires-Python: >=3.11
License-File: LICENSE
Requires-Dist: matplotlib
Requires-Dist: scipy
Requires-Dist: ipython
Requires-Dist: unidecode
Requires-Dist: numpy
Requires-Dist: psutil
Requires-Dist: mpmath
Provides-Extra: dev
Requires-Dist: ruff; extra == "dev"
Requires-Dist: setuptools-scm; extra == "dev"
Dynamic: license-file
